GPXTweaker/GPXTweaker.cfg
GPXTweaker/GPXTweaker.py
GPXTweaker/README.md
GPXTweaker/__init__.py
GPXTweaker/jpegtran.bat
GPXTweaker/test.py
gpxtweaker-1.19.2.dist-info/licenses/LICENSE
gpxtweaker-1.19.2.dist-info/METADATA
gpxtweaker-1.19.2.dist-info/WHEEL
gpxtweaker-1.19.2.dist-info/top_level.txt
gpxtweaker-1.19.2.dist-info/RECORD
