Metadata-Version: 2.4
Name: GPXTweaker
Version: 1.19.2
Summary: A script in Python 3 to visualize, in 2D and 3D, and edit GPX tracks
Home-page: https://github.com/PCigales/GPXTweaker
Author: PCigales
License: GPL-3.0-or-later
Project-URL: Bug Tracker, https://github.com/PCigales/GPXTweaker/issues
Keywords: gpx,gis,wms,wmts,3d,wgs84,mercator,geotag
Platform: win64
Classifier: Programming Language :: Python :: 3
Classifier: Operating System :: Microsoft :: Windows
Classifier: Development Status :: 5 - Production/Stable
Classifier: Topic :: Scientific/Engineering :: GIS
Requires-Python: >=3.8
License-File: LICENSE
Dynamic: license-file
